{
    "required": true,
    "minVersion": "0.8",
    "package": "turniplabs.halplibe.mixin",
    "compatibilityLevel": "JAVA_8",
    "mixins": [
        "accessors.BlockAccessor",
        "accessors.BlockFireAccessor",
        "accessors.CraftingManagerAccessor",
        "accessors.DimensionAccessor",
        "accessors.EntityListAccessor",
        "accessors.LanguageAccessor",
        "accessors.RecipesBlastFurnaceAccessor",
        "accessors.RecipesFurnaceAccessor",
        "accessors.RenderManagerAccessor",
        "accessors.RenderPlayerAccessor",
        "accessors.TileEntityAccessor",
        "accessors.TileEntityRendererAccessor",
        "mixins.BlockFireMixin",
        "mixins.BlockSoundDispatcherMixin",
        "mixins.EntityClientPlayerMPMixin",
        "mixins.I18nMixin",
        "mixins.RenderEngineMixin",
        "mixins.RenderGlobalMixin"
    ],
    "client": [
    ],
    "injectors": {
        "defaultRequire": 1
  }
}
